{"createdAt":"2025-02-12T01:09:23.037Z","updatedAt":"2025-02-12T01:27:07.000Z","id":"kWcKMCBw9oyKJMI6","name":"Create, add an attachment, and send a draft using Microsoft Outlook","active":false,"nodes":[{"parameters":{},"name":"On clicking 'execute'","type":"n8n-nodes-base.manualTrigger","position":[0,0],"typeVersion":1,"id":"73f5520e-a296-4992-b4c7-4295565d42ea"},{"parameters":{"resource":"draft","subject":"Hello from n8n!","bodyContent":"<h1>Hello from n8n!</h1> <p>We are sending this email using the Microsoft Outlook node in <a href=\"https://n8n.io\">n8n</a></p> <p>Best,</p> <p>Sender</p>","additionalFields":{"bodyContentType":"html"}},"name":"Microsoft Outlook","type":"n8n-nodes-base.microsoftOutlook","position":[200,0],"typeVersion":1,"id":"46bb2366-6628-4f8c-b992-bd904e10cc89","credentials":{"microsoftOutlookOAuth2Api":{"id":null,"name":"Micrsoft Outlook Credentials"}}},{"parameters":{"url":"https://n8n.io/n8n-logo.png","responseFormat":"file","options":{}},"name":"HTTP Request","type":"n8n-nodes-base.httpRequest","position":[400,0],"typeVersion":1,"id":"395eeff3-2efe-4851-8f51-ca105f389d7a"},{"parameters":{"resource":"messageAttachment","messageId":"={{$node[\"Microsoft Outlook\"].json[\"id\"]}}","additionalFields":{"fileName":"n8n.png"}},"name":"Microsoft Outlook1","type":"n8n-nodes-base.microsoftOutlook","position":[600,0],"typeVersion":1,"id":"aa942c0c-0201-45c9-abb0-a58d35223c1f","credentials":{"microsoftOutlookOAuth2Api":{"id":null,"name":"Micrsoft Outlook Credentials"}}},{"parameters":{"resource":"draft","operation":"send","messageId":"={{$node[\"Microsoft Outlook\"].json[\"id\"]}}","additionalFields":{"recipients":"abc@example.com"}},"name":"Microsoft Outlook2","type":"n8n-nodes-base.microsoftOutlook","position":[800,0],"typeVersion":1,"id":"963d0834-62bb-4b0a-8413-bb198050b04f","credentials":{"microsoftOutlookOAuth2Api":{"id":null,"name":"Micrsoft Outlook Credentials"}}}],"connections":{"HTTP Request":{"main":[[{"node":"Microsoft Outlook1","type":"main","index":0}]]},"Microsoft Outlook":{"main":[[{"node":"HTTP Request","type":"main","index":0}]]},"Microsoft Outlook1":{"main":[[{"node":"Microsoft Outlook2","type":"main","index":0}]]},"On clicking 'execute'":{"main":[[{"node":"Microsoft Outlook","type":"main","index":0}]]}},"settings":{"executionOrder":"v1"},"staticData":null,"meta":null,"pinData":{},"versionId":"3ff14ab0-25f3-4ed5-97e2-4819db7cd9d4","triggerCount":0,"tags":[{"createdAt":"2025-02-12T01:27:06.022Z","updatedAt":"2025-02-12T01:27:06.022Z","id":"XinLwiwNst8mTVBz","name":"OFFICE_AUTOMATION"},{"createdAt":"2025-02-11T23:59:41.483Z","updatedAt":"2025-02-14T16:18:26.979Z","id":"dzhL8PxGOvRSKz2J","name":"ANCORA IN TEST"}]}